aioloki/__init__.py
aioloki/handler.py
aioloki/types.py
aioloki-0.0.1a1.dist-info/LICENSE
aioloki-0.0.1a1.dist-info/METADATA
aioloki-0.0.1a1.dist-info/WHEEL
aioloki-0.0.1a1.dist-info/top_level.txt
aioloki-0.0.1a1.dist-info/RECORD
